Workbook

Sheet 1. Monthly P&L
A1: MONTHLY PROFIT & LOSS — FY 2024
A2: Blue values = data inputs (edit these) | Black values = formulas (do not edit)
A3: Month | B3: Rev — Actual ($K) | C3: Rev — Budget ($K) | D3: Rev Variance ($K) | E3: Exp — Actual ($K) | F3: Exp — Budget ($K) | G3: Exp Variance ($K) | H3: Net Profit ($K) | I3: Profit Margin (%)
A4: Jan | B4: 720 | C4: 700 | D4: =B4-C4 -> 20 | E4: 510 | F4: 500 | G4: =E4-F4 -> 10 | H4: =B4-E4 -> 210 | I4: =IF(B4=0,0,H4/B4) -> 0.29166667
A5: Feb | B5: 680 | C5: 710 | D5: =B5-C5 -> -30 | E5: 490 | F5: 505 | G5: =E5-F5 -> -15 | H5: =B5-E5 -> 190 | I5: =IF(B5=0,0,H5/B5) -> 0.27941176
A6: Mar | B6: 750 | C6: 730 | D6: =B6-C6 -> 20 | E6: 530 | F6: 520 | G6: =E6-F6 -> 10 | H6: =B6-E6 -> 220 | I6: =IF(B6=0,0,H6/B6) -> 0.29333333
A7: Apr | B7: 810 | C7: 790 | D7: =B7-C7 -> 20 | E7: 580 | F7: 570 | G7: =E7-F7 -> 10 | H7: =B7-E7 -> 230 | I7: =IF(B7=0,0,H7/B7) -> 0.28395062
A8: May | B8: 760 | C8: 790 | D8: =B8-C8 -> -30 | E8: 560 | F8: 570 | G8: =E8-F8 -> -10 | H8: =B8-E8 -> 200 | I8: =IF(B8=0,0,H8/B8) -> 0.26315789
A9: Jun | B9: 870 | C9: 840 | D9: =B9-C9 -> 30 | E9: 620 | F9: 610 | G9: =E9-F9 -> 10 | H9: =B9-E9 -> 250 | I9: =IF(B9=0,0,H9/B9) -> 0.28735632
A10: Jul | B10: 980 | C10: 930 | D10: =B10-C10 -> 50 | E10: 710 | F10: 695 | G10: =E10-F10 -> 15 | H10: =B10-E10 -> 270 | I10: =IF(B10=0,0,H10/B10) -> 0.2755102
A11: Aug | B11: 920 | C11: 900 | D11: =B11-C11 -> 20 | E11: 680 | F11: 670 | G11: =E11-F11 -> 10 | H11: =B11-E11 -> 240 | I11: =IF(B11=0,0,H11/B11) -> 0.26086957
A12: Sep | B12: 850 | C12: 860 | D12: =B12-C12 -> -10 | E12: 620 | F12: 615 | G12: =E12-F12 -> 5 | H12: =B12-E12 -> 230 | I12: =IF(B12=0,0,H12/B12) -> 0.27058824
A13: Oct | B13: 890 | C13: 870 | D13: =B13-C13 -> 20 | E13: 650 | F13: 640 | G13: =E13-F13 -> 10 | H13: =B13-E13 -> 240 | I13: =IF(B13=0,0,H13/B13) -> 0.26966292
A14: Nov | B14: 910 | C14: 880 | D14: =B14-C14 -> 30 | E14: 670 | F14: 660 | G14: =E14-F14 -> 10 | H14: =B14-E14 -> 240 | I14: =IF(B14=0,0,H14/B14) -> 0.26373626
A15: Dec | B15: 960 | C15: 940 | D15: =B15-C15 -> 20 | E15: 700 | F15: 690 | G15: =E15-F15 -> 10 | H15: =B15-E15 -> 260 | I15: =IF(B15=0,0,H15/B15) -> 0.27083333
A16: TOTAL / AVG | B16: =SUM(B4:B15) -> 10100 | C16: =SUM(C4:C15) -> 9940 | D16: =SUM(D4:D15) -> 160 | E16: =SUM(E4:E15) -> 7320 | F16: =SUM(F4:F15) -> 7245 | G16: =SUM(G4:G15) -> 75 | H16: =SUM(H4:H15) -> 2780 | I16: =AVERAGE(I4:I15) -> 0.27583976

Sheet 2. Budget vs Actual
A1: BUDGET VS ACTUAL — BY DEPARTMENT (YTD FY 2024)
A2: Blue values = data inputs | Black values = formulas
A3: Department | B3: Budget ($K) | C3: Actual ($K) | D3: Variance ($K) | E3: Variance (%) | F3: % Utilised | G3: Status
A4: Research | B4: 1200 | C4: 1080 | D4: =C4-B4 -> -120 | E4: =IF(B4=0,0,D4/B4) -> -0.1 | F4: =IF(B4=0,0,C4/B4) -> 0.9 | G4: =IF(D4<0,"Over Budget",IF(D4=0,"On Budget","Under Budget")) -> Over Budget
A5: Finance & Admin | B5: 480 | C5: 440 | D5: =C5-B5 -> -40 | E5: =IF(B5=0,0,D5/B5) -> -0.083333333 | F5: =IF(B5=0,0,C5/B5) -> 0.91666667 | G5: =IF(D5<0,"Over Budget",IF(D5=0,"On Budget","Under Budget")) -> Over Budget
A6: Human Resources | B6: 320 | C6: 310 | D6: =C6-B6 -> -10 | E6: =IF(B6=0,0,D6/B6) -> -0.03125 | F6: =IF(B6=0,0,C6/B6) -> 0.96875 | G6: =IF(D6<0,"Over Budget",IF(D6=0,"On Budget","Under Budget")) -> Over Budget
A7: ICT | B7: 560 | C7: 545 | D7: =C7-B7 -> -15 | E7: =IF(B7=0,0,D7/B7) -> -0.026785714 | F7: =IF(B7=0,0,C7/B7) -> 0.97321429 | G7: =IF(D7<0,"Over Budget",IF(D7=0,"On Budget","Under Budget")) -> Over Budget
A8: Programmes | B8: 1800 | C8: 1760 | D8: =C8-B8 -> -40 | E8: =IF(B8=0,0,D8/B8) -> -0.022222222 | F8: =IF(B8=0,0,C8/B8) -> 0.97777778 | G8: =IF(D8<0,"Over Budget",IF(D8=0,"On Budget","Under Budget")) -> Over Budget
A9: Communications | B9: 240 | C9: 260 | D9: =C9-B9 -> 20 | E9: =IF(B9=0,0,D9/B9) -> 0.083333333 | F9: =IF(B9=0,0,C9/B9) -> 1.0833333 | G9: =IF(D9<0,"Over Budget",IF(D9=0,"On Budget","Under Budget")) -> Under Budget
A10: TOTAL | B10: =SUM(B4:B9) -> 4600 | C10: =SUM(C4:C9) -> 4395 | D10: =SUM(D4:D9) -> -205 | E10: =IF(B10=0,0,D10/B10) -> -0.044565217 | F10: =IF(B10=0,0,C10/B10) -> 0.95543478

Sheet 3. Expense Categories
A1: EXPENSE BREAKDOWN BY CATEGORY — YTD FY 2024
A2: Blue values = data inputs | Black values = formulas
A3: Expense Category | B3: Amount ($K) | C3: % of Total | D3: Budget ($K) | E3: Variance ($K)
A4: Personnel & Salaries | B4: 2745 | C4: =IF(B10=0,0,B4/B10) -> 0.39468009 | D4: 2800 | E4: =B4-D4 -> -55
A5: Operations & Admin | B5: 1342 | C5: =IF(B10=0,0,B5/B10) -> 0.19295471 | D5: 1300 | E5: =B5-D5 -> 42
A6: Project Delivery | B6: 1221 | C6: =IF(B10=0,0,B6/B10) -> 0.17555715 | D6: 1200 | E6: =B6-D6 -> 21
A7: Overhead & Facilities | B7: 793 | C7: =IF(B10=0,0,B7/B10) -> 0.11401869 | D7: 800 | E7: =B7-D7 -> -7
A8: Travel & Logistics | B8: 366 | C8: =IF(B10=0,0,B8/B10) -> 0.052624012 | D8: 350 | E8: =B8-D8 -> 16
A9: Capacity Building | B9: 488 | C9: =IF(B10=0,0,B9/B10) -> 0.070165349 | D9: 450 | E9: =B9-D9 -> 38
A10: TOTAL | B10: =SUM(B4:B9) -> 6955 | C10: =SUM(C4:C9) -> 1 | D10: =SUM(D4:D9) -> 6900 | E10: =SUM(E4:E9) -> 55

Sheet 4. KPI Summary
A1: KEY PERFORMANCE INDICATORS — FY 2024
A2: All values auto-calculated from your data sheets — do not edit this sheet directly
A3: KPI | B3: Value | C3: Target | D3: Status
A4: Total Revenue (YTD) | B4: ='1. Monthly P&L'!B16 -> 10100 | C4: ='1. Monthly P&L'!C16 -> 9940 | D4: =IF(B4>=C4,"✔ On Target","✘ Below Target") -> ✔ On Target
A5: Total Expenses (YTD) | B5: ='1. Monthly P&L'!E16 -> 7320 | C5: ='1. Monthly P&L'!F16 -> 7245 | D5: =IF(B5>=C5,"✔ On Target","✘ Below Target") -> ✔ On Target
A6: Net Profit (YTD) | B6: ='1. Monthly P&L'!H16 -> 2780 | C6: — | D6: —
A7: Avg Profit Margin | B7: ='1. Monthly P&L'!I16 -> 0.27583976 | C7: 0.25 | D7: =IF(B7>=C7,"✔ On Target","✘ Below Target") -> ✔ On Target
A8: Budget Utilisation (Overall) | B8: ='2. Budget vs Actual'!F10 -> 0.95543478 | C8: 0.95 | D8: =IF(B8>=C8,"✔ On Target","✘ Below Target") -> ✔ On Target
A9: Cost Recovery Rate | B9: ='3. Expense Categories'!B10/'1. Monthly P&L'!B16 -> 0.68861386 | C9: 0.95 | D9: =IF(B9>=C9,"✔ On Target","✘ Below Target") -> ✘ Below Target
A10: Revenue vs Budget Variance | B10: ='1. Monthly P&L'!D16 -> 160 | C10: 0 | D10: =IF(B10>=C10,"✔ On Target","✘ Below Target") -> ✔ On Target
A11: Expense vs Budget Variance | B11: ='1. Monthly P&L'!G16 -> 75 | C11: 0 | D11: =IF(B11>=C11,"✔ On Target","✘ Below Target") -> ✔ On Target
